[
  {
    "CaseTypeID": "CIVIL${CCD_DEF_VERSION}",
    "CaseFieldID": "caseBundles",
    "ListElementCode": "id",
    "UserRole": "caseworker-civil-systemupdate",
    "CRUD": "CRU"
  },
  {
    "CaseTypeID": "CIVIL${CCD_DEF_VERSION}",
    "CaseFieldID": "caseBundles",
    "ListElementCode": "title",
    "UserRole": "caseworker-civil-systemupdate",
    "CRUD": "CRU"
  },
  {
    "CaseTypeID": "CIVIL${CCD_DEF_VERSION}",
    "CaseFieldID": "caseBundles",
    "ListElementCode": "description",
    "UserRole": "caseworker-civil-systemupdate",
    "CRUD": "CRU"
  },
  {
    "CaseTypeID": "CIVIL${CCD_DEF_VERSION}",
    "CaseFieldID": "caseBundles",
    "ListElementCode": "eligibleForStitching",
    "UserRole": "caseworker-civil-systemupdate",
    "CRUD": "CRU"
  },
  {
    "CaseTypeID": "CIVIL${CCD_DEF_VERSION}",
    "CaseFieldID": "caseBundles",
    "ListElementCode": "eligibleForCloning",
    "UserRole": "caseworker-civil-systemupdate",
    "CRUD": "CRU"
  },
  {
    "CaseTypeID": "CIVIL${CCD_DEF_VERSION}",
    "CaseFieldID": "caseBundles",
    "ListElementCode": "documents",
    "UserRole": "caseworker-civil-systemupdate",
    "CRUD": "CRU"
  },
  {
    "CaseTypeID": "CIVIL${CCD_DEF_VERSION}",
    "CaseFieldID": "caseBundles",
    "ListElementCode": "folders",
    "UserRole": "caseworker-civil-systemupdate",
    "CRUD": "CRU"
  },
  {
    "CaseTypeID": "CIVIL${CCD_DEF_VERSION}",
    "CaseFieldID": "caseBundles",
    "ListElementCode": "stitchStatus",
    "UserRole": "caseworker-civil-systemupdate",
    "CRUD": "CRU"
  },
  {
    "CaseTypeID": "CIVIL${CCD_DEF_VERSION}",
    "CaseFieldID": "caseBundles",
    "ListElementCode": "stitchedDocument",
    "UserRole": "caseworker-civil-systemupdate",
    "CRUD": "CRU"
  },
  {
    "CaseTypeID": "CIVIL${CCD_DEF_VERSION}",
    "CaseFieldID": "caseBundles",
    "ListElementCode": "hasCoversheets",
    "UserRole": "caseworker-civil-systemupdate",
    "CRUD": "CRU"
  },
  {
    "CaseTypeID": "CIVIL${CCD_DEF_VERSION}",
    "CaseFieldID": "caseBundles",
    "ListElementCode": "hasTableOfContents",
    "UserRole": "caseworker-civil-systemupdate",
    "CRUD": "CRU"
  },
  {
    "CaseTypeID": "CIVIL${CCD_DEF_VERSION}",
    "CaseFieldID": "caseBundles",
    "ListElementCode": "paginationStyle",
    "UserRole": "caseworker-civil-systemupdate",
    "CRUD": "CRU"
  },
  {
    "CaseTypeID": "CIVIL${CCD_DEF_VERSION}",
    "CaseFieldID": "caseBundles",
    "ListElementCode": "pageNumberFormat",
    "UserRole": "caseworker-civil-systemupdate",
    "CRUD": "CRU"
  },
  {
    "CaseTypeID": "CIVIL${CCD_DEF_VERSION}",
    "CaseFieldID": "caseBundles",
    "ListElementCode": "stitchingFailureMessage",
    "UserRole": "caseworker-civil-systemupdate",
    "CRUD": "CRU"
  },
  {
    "CaseTypeID": "CIVIL${CCD_DEF_VERSION}",
    "CaseFieldID": "caseBundles",
    "ListElementCode": "coverpageTemplate",
    "UserRole": "caseworker-civil-systemupdate",
    "CRUD": "CRU"
  },
  {
    "CaseTypeID": "CIVIL${CCD_DEF_VERSION}",
    "CaseFieldID": "caseBundles",
    "ListElementCode": "enableEmailNotification",
    "UserRole": "caseworker-civil-systemupdate",
    "CRUD": "CRU"
  },
  {
    "CaseTypeID": "CIVIL${CCD_DEF_VERSION}",
    "CaseFieldID": "caseBundles",
    "ListElementCode": "fileName",
    "UserRole": "caseworker-civil-systemupdate",
    "CRUD": "CRU"
  },
  {
    "CaseTypeID": "CIVIL${CCD_DEF_VERSION}",
    "CaseFieldID": "caseBundles",
    "ListElementCode": "fileNameIdentifier",
    "UserRole": "caseworker-civil-systemupdate",
    "CRUD": "CRU"
  },
  {
    "CaseTypeID": "CIVIL${CCD_DEF_VERSION}",
    "CaseFieldID": "caseBundles",
    "ListElementCode": "bundleHearingDate",
    "UserRole": "caseworker-civil-systemupdate",
    "CRUD": "CRU"
  },
  {
    "CaseTypeID": "CIVIL${CCD_DEF_VERSION}",
    "CaseFieldID": "caseBundles",
    "ListElementCode": "createdOn",
    "UserRole": "caseworker-civil-systemupdate",
    "CRUD": "CRU"
  },
  {
    "CaseTypeID": "CIVIL${CCD_DEF_VERSION}",
    "CaseFieldID": "caseBundles",
    "ListElementCode": "uploadedBy",
    "UserRole": "caseworker-civil-systemupdate",
    "CRUD": "CRU"
  }
]
