[
  {
    "CaseTypeID": "CIVIL${CCD_DEF_VERSION}",
    "CaseFieldID": "applicant1DQFixedRecoverableCosts",
    "AccessControl": [
      {
        "UserRoles": [
          "CITIZEN-CLAIMANT-PROFILE"
        ],
        "CRUD": "CRU"
      }
    ]
  },
  {
    "CaseTypeID": "CIVIL${CCD_DEF_VERSION}",
    "CaseFieldID": "applicant2DQFixedRecoverableCosts",
    "AccessControl": [
      {
        "UserRoles": [
          "CITIZEN-CLAIMANT-PROFILE"
        ],
        "CRUD": "CRU"
      }
    ]
  },
  {
    "CaseTypeID": "CIVIL${CCD_DEF_VERSION}",
    "CaseFieldID": "respondent1DQFixedRecoverableCosts",
    "AccessControl": [
      {
        "UserRoles": [
          "CITIZEN-CLAIMANT-PROFILE"
        ],
        "CRUD": "R"
      }
    ]
  },
  {
    "CaseTypeID": "CIVIL${CCD_DEF_VERSION}",
    "CaseFieldID": "respondent2DQFixedRecoverableCosts",
    "AccessControl": [
      {
        "UserRoles": [
          "CITIZEN-CLAIMANT-PROFILE"
        ],
        "CRUD": "R"
      }
    ]
  }
]
