[
  {
    "CaseTypeID": "CIVIL${CCD_DEF_VERSION}",
    "CaseFieldID": "bundleLabel",
    "AccessControl": [
      {
        "UserRoles": [
          "APP-SOL-UNSPEC-PROFILE",
          "APP-SOL-SPEC-PROFILE",
          "RES-SOL-ONE-UNSPEC-PROFILE",
          "RES-SOL-ONE-SPEC-PROFILE",
          "RES-SOL-TWO-UNSPEC-PROFILE",
          "RES-SOL-TWO-SPEC-PROFILE"
        ],
        "CRUD": "CRU"
      },
      {
        "UserRoles": [
          "caseworker-civil-admin"
        ],
        "CRUD": "R"
      }
    ]
  },
  {
    "CaseTypeID": "CIVIL${CCD_DEF_VERSION}",
    "CaseFieldID": "bundleSelectionEvidence",
    "AccessControl": [
      {
        "UserRoles": [
          "APP-SOL-UNSPEC-PROFILE",
          "APP-SOL-SPEC-PROFILE",
          "RES-SOL-ONE-UNSPEC-PROFILE",
          "RES-SOL-ONE-SPEC-PROFILE",
          "RES-SOL-TWO-UNSPEC-PROFILE",
          "RES-SOL-TWO-SPEC-PROFILE"
        ],
        "CRUD": "CRU"
      },
      {
        "UserRoles": [
          "caseworker-civil-admin"
        ],
        "CRUD": "R"
      }
    ]
  },
  {
    "CaseTypeID": "CIVIL${CCD_DEF_VERSION}",
    "CaseFieldID": "bundleEvidence",
    "AccessControl": [
      {
        "UserRoles": [
          "APP-SOL-UNSPEC-PROFILE",
          "APP-SOL-SPEC-PROFILE",
          "RES-SOL-ONE-UNSPEC-PROFILE",
          "RES-SOL-ONE-SPEC-PROFILE",
          "RES-SOL-TWO-UNSPEC-PROFILE",
          "RES-SOL-TWO-SPEC-PROFILE",
          "judge-profile",
          "hearing-schedule-access"
        ],
        "CRUD": "CRU"
      },
      {
        "UserRoles": [
          "caseworker-civil-admin",
          "caseworker-civil-systemupdate"
        ],
        "CRUD": "R"
      }
    ]
  }
]
