[ {
  "CaseEventID" : "CREATE_CLAIM_SPEC",
  "CaseFieldID" : "specApplicantCorrespondenceAddressdetails",
  "ListElementCode" : "AddressLine1",
  "ID" : "SpecCorrespondenceAddress",
  "FieldDisplayOrder" : 1
}, {
  "CaseEventID" : "CREATE_CLAIM_SPEC",
  "CaseFieldID" : "specApplicantCorrespondenceAddressdetails",
  "ListElementCode" : "AddressLine2",
  "ID" : "SpecCorrespondenceAddress",
  "FieldDisplayOrder" : 2
}, {
  "CaseEventID" : "CREATE_CLAIM_SPEC",
  "CaseFieldID" : "specApplicantCorrespondenceAddressdetails",
  "ListElementCode" : "AddressLine3",
  "ID" : "SpecCorrespondenceAddress",
  "FieldDisplayOrder" : 3
}, {
  "CaseEventID" : "CREATE_CLAIM_SPEC",
  "CaseFieldID" : "specApplicantCorrespondenceAddressdetails",
  "ListElementCode" : "PostTown",
  "ID" : "SpecCorrespondenceAddress",
  "FieldDisplayOrder" : 4
}, {
  "CaseEventID" : "CREATE_CLAIM_SPEC",
  "CaseFieldID" : "specApplicantCorrespondenceAddressdetails",
  "ListElementCode" : "County",
  "ID" : "SpecCorrespondenceAddress",
  "FieldDisplayOrder" : 5
}, {
  "CaseEventID" : "CREATE_CLAIM_SPEC",
  "CaseFieldID" : "specApplicantCorrespondenceAddressdetails",
  "ListElementCode" : "Country",
  "ID" : "SpecCorrespondenceAddress",
  "FieldDisplayOrder" : 6
}, {
  "CaseEventID" : "CREATE_CLAIM_SPEC",
  "CaseFieldID" : "specApplicantCorrespondenceAddressdetails",
  "ListElementCode" : "PostCode",
  "ID" : "SpecCorrespondenceAddress",
  "FieldDisplayOrder" : 7
} ]